[
    {
        "x": 17,
        "y": 11
    },
    {
        "x": 12,
        "y": 11
    },
    {
        "x": 3,
        "y": 9
    },
    {
        "x": 5,
        "y": 7
    },
    {
        "x": 16,
        "y": 4
    },
    {
        "x": 17,
        "y": 2
    },
    {
        "x": 12,
        "y": 2
    },
    {
        "x": 6,
        "y": 2
    },
    {
        "x": 9,
        "y": 6
    },
    {
        "x": 17,
        "y": 7
    },
    {
        "x": 9,
        "y": 9
    },
    {
        "x": 4,
        "y": 9
    },
    {
        "x": 6,
        "y": 5
    }
]